<?xml version = '1.0'?>
<archangel>
  <skysig units='DN'>
    0.15
  </skysig>
  <scale>
    1.0
  </scale>
  <zeropoint>
    20.9360
  </zeropoint>
  <sky units='DN'>
    0.02
  </sky>
  <array name='prf'>
    <axis name='INTENS'>
      1.07423256E+02
      1.05499214E+02
      1.02622078E+02
      9.95793381E+01
      9.60381546E+01
      9.22016144E+01
      8.81407013E+01
      8.40071716E+01
      7.95887909E+01
      7.50660248E+01
      7.03753510E+01
      6.55465698E+01
      6.08969269E+01
      5.66909180E+01
      5.26011124E+01
      4.86270561E+01
      4.52356339E+01
      4.19159431E+01
      3.90465775E+01
      3.64497948E+01
      3.38155556E+01
      3.15554161E+01
      2.96204510E+01
      2.74742947E+01
      2.56140308E+01
      2.42124271E+01
      2.30631886E+01
      2.19621620E+01
      2.09276791E+01
      2.01040440E+01
      1.90784664E+01
      1.81154690E+01
      1.62624283E+01
      1.47289047E+01
      1.38696365E+01
      1.21116610E+01
      1.10886688E+01
      8.74455452E+00
      6.74849224E+00
      5.50815010E+00
      4.49177361E+00
      3.45814586E+00
      2.51623034E+00
      1.71056032E+00
      1.05383098E+00
      5.94282389E-01
      3.89098287E-01
      2.60899961E-01
      1.04977712E-01
      3.15407440E-02
      3.20842043E-02
      7.43907988E-02
    </axis>
    <axis name='INT_ERR'>
      -6.20864751E-03
      7.52952008E-04
      -7.94561207E-03
      -5.14733279E-03
      -2.30990583E-03
      -5.96027967E-05
      8.18515429E-04
      2.27039913E-03
      -1.08169613E-03
      -1.75045361E-03
      -1.80558173E-03
      7.01714773E-04
      9.22755455E-04
      8.18410888E-04
      5.49089280E-04
      1.78536691E-03
      3.00473603E-03
      4.85056592E-03
      5.15747815E-03
      5.45688672E-03
      1.09787686E-02
      1.49233975E-02
      1.28173251E-02
      8.48224480E-03
      1.90731167E-04
      -9.38014127E-03
      -1.28094815E-02
      -9.37161129E-03
      -1.26402471E-02
      -1.38967354E-02
      -9.86082666E-03
      -6.94951415E-03
      1.11508397E-02
      -2.20720028E-03
      1.13366293E-02
      9.13320389E-03
      6.89078448E-03
      7.30036059E-03
      2.14733146E-02
      1.10725854E-02
      5.16733481E-03
      5.07593714E-03
      3.13348719E-03
      -5.98850381E-03
      -1.37158772E-02
      -5.61949564E-03
      5.87145276E-02
      9.24112089E-03
      1.45548861E-02
      -3.84045392E-02
      1.06450552E-02
      2.55694926E-01
    </axis>
    <axis name='GRAD'>
      -2.18756371E+01
      -2.23948841E+01
      -2.40433140E+01
      -2.42543087E+01
      -2.43093834E+01
      -2.46547031E+01
      -2.44326038E+01
      -2.33764229E+01
      -2.20822315E+01
      -2.10445309E+01
      -1.96939354E+01
      -1.75910416E+01
      -1.51810246E+01
      -1.33641777E+01
      -1.17013931E+01
      -9.66762447E+00
      -8.18802071E+00
      -7.01918888E+00
      -5.87644100E+00
      -5.01618147E+00
      -4.24982166E+00
      -3.64325190E+00
      -3.19658923E+00
      -2.69910765E+00
      -2.20372343E+00
      -1.78018296E+00
      -1.51480532E+00
      -1.32453024E+00
      -1.14903963E+00
      -1.02147746E+00
      -9.28628922E-01
      -9.08256710E-01
      -7.95830071E-01
      -6.52657866E-01
      -6.45785093E-01
      -5.65372288E-01
      -5.13431013E-01
      -5.77446640E-01
      -4.15074557E-01
      -2.98744380E-01
      -2.68194169E-01
      -2.38861024E-01
      -1.86607227E-01
      -1.27689302E-01
      -6.94293082E-02
      -5.84250987E-02
      -1.27172153E-02
      -1.17054591E-02
      -1.71335656E-02
      -3.84004926E-03
      1.05688730E-02
      -1.10257312E-03
    </axis>
    <axis name='RAD'>
      1.05332458E+00
      1.15865707E+00
      1.27452278E+00
      1.40197515E+00
      1.54217267E+00
      1.69639003E+00
      1.86602914E+00
      2.05263209E+00
      2.25789547E+00
      2.48368502E+00
      2.73205352E+00
      3.00525904E+00
      3.30578494E+00
      3.63636351E+00
      4.00000000E+00
      4.40000010E+00
      4.84000015E+00
      5.32400036E+00
      5.85640049E+00
      6.44204044E+00
      7.08624458E+00
      7.79486942E+00
      8.57435608E+00
      9.43179226E+00
      1.03749714E+01
      1.14124689E+01
      1.25537157E+01
      1.38090878E+01
      1.51899967E+01
      1.67089958E+01
      1.83798962E+01
      2.02178860E+01
      2.22396755E+01
      2.44636440E+01
      2.69100094E+01
      2.96010113E+01
      3.25611115E+01
      3.58172226E+01
      3.93989449E+01
      4.33388405E+01
      4.76727257E+01
      5.24399986E+01
      5.76839981E+01
      6.34524002E+01
      6.97976379E+01
      7.67774048E+01
      8.44551468E+01
      9.29006653E+01
      1.02190735E+02
      1.12409813E+02
      1.23650795E+02
      1.36015884E+02
    </axis>
    <axis name='RMSRES'>
      8.22287798E-01
      8.22225690E-01
      8.00916851E-01
      6.82201207E-01
      6.44050777E-01
      5.61541975E-01
      4.91578102E-01
      5.07622063E-01
      4.61903155E-01
      3.87949646E-01
      3.20123851E-01
      2.33131945E-01
      2.48012781E-01
      2.99633503E-01
      3.24556440E-01
      3.50142688E-01
      4.29848671E-01
      4.48997766E-01
      4.83264744E-01
      4.70987380E-01
      5.09849012E-01
      5.11266112E-01
      4.79879141E-01
      5.13909519E-01
      5.92454255E-01
      6.72375977E-01
      6.80370688E-01
      6.08576536E-01
      5.88985085E-01
      7.64197707E-01
      8.65858495E-01
      1.10642374E+00
      6.98797822E-01
      4.64932740E-01
      4.06756014E-01
      4.34417546E-01
      5.44302523E-01
      5.73800743E-01
      5.71704328E-01
      5.27943909E-01
      4.20889109E-01
      4.46374297E-01
      3.58359486E-01
      3.30205858E-01
      3.12629402E-01
      2.97744095E-01
      2.54824698E-01
      2.50642210E-01
      2.29732662E-01
      2.30821341E-01
      2.32340097E-01
      1.59933805E-01
    </axis>
    <axis name='FOURSL'>
      -1.33779701E-02
      -3.64973466E-03
      3.17892316E-03
      9.14859178E-04
      2.91821896E-03
      4.23975987E-03
      8.51337041E-04
      5.25910221E-03
      4.08408185E-03
      3.10070417E-03
      2.23401748E-03
      -1.57248214E-04
      1.17573142E-03
      2.51107640E-03
      1.28629024E-03
      2.37876875E-03
      6.33632764E-03
      4.92423819E-03
      4.80406079E-03
      2.05138209E-03
      3.90850008E-03
      2.12709815E-03
      1.64152461E-03
      2.53334036E-03
      1.02632046E-02
      1.26249203E-02
      1.18481973E-02
      5.69981523E-03
      -8.19066167E-03
      -2.63323821E-02
      -3.80082317E-02
      -3.12478952E-02
      -3.49115464E-03
      -8.00575782E-03
      -1.74485482E-02
      3.09736980E-03
      -1.75029633E-03
      -1.12017216E-04
      -2.00461620E-03
      -2.04778332E-02
      -2.02272125E-02
      -2.47399192E-02
      -1.25897061E-02
      -1.26332492E-02
      2.59692734E-03
      -5.29239839E-03
      -5.45893945E-02
      6.38781786E-02
      7.65728951E-03
      -1.71906486E-01
      -2.91500002E-01
      -6.30061477E-02
    </axis>
    <axis name='ITER'>
      9.00000000E+00
      9.00000000E+00
      -3.00000000E+01
      1.50000000E+01
      8.00000000E+00
      1.80000000E+01
      8.00000000E+00
      1.60000000E+01
      -3.00000000E+01
      1.20000000E+01
      1.10000000E+01
      9.00000000E+00
      1.70000000E+01
      8.00000000E+00
      2.20000000E+01
      9.00000000E+00
      -3.00000000E+01
      1.00000000E+01
      8.00000000E+00
      1.20000000E+01
      1.10000000E+01
      8.00000000E+00
      9.00000000E+00
      1.30000000E+01
      1.10000000E+01
      8.00000000E+00
      9.00000000E+00
      8.00000000E+00
      8.00000000E+00
      1.00000000E+01
      9.00000000E+00
      3.00000000E+00
      -1.00000000E+00
      -3.00000000E+01
      -3.00000000E+01
      -3.00000000E+01
      -3.00000000E+01
      -3.00000000E+01
      -3.00000000E+01
      -3.00000000E+01
      1.90000000E+01
      9.00000000E+00
      1.30000000E+01
      1.00000000E+01
      8.00000000E+00
      1.00000000E+00
      1.00000000E+00
      1.00000000E+00
      1.00000000E+00
      1.00000000E+00
      1.00000000E+00
      1.00000000E+00
    </axis>
    <axis name='NUM'>
      3.60000000E+01
      3.60000000E+01
      3.60000000E+01
      3.60000000E+01
      3.60000000E+01
      3.60000000E+01
      3.60000000E+01
      3.60000000E+01
      3.60000000E+01
      3.60000000E+01
      3.60000000E+01
      3.60000000E+01
      3.60000000E+01
      3.60000000E+01
      3.60000000E+01
      3.60000000E+01
      3.60000000E+01
      3.60000000E+01
      3.60000000E+01
      3.60000000E+01
      4.00000000E+01
      4.40000000E+01
      4.90000000E+01
      5.50000000E+01
      6.10000000E+01
      6.70000000E+01
      7.40000000E+01
      8.20000000E+01
      9.10000000E+01
      1.00000000E+02
      1.11000000E+02
      3.70000000E+01
      3.60000000E+01
      4.50000000E+01
      3.50000000E+01
      4.80000000E+01
      5.90000000E+01
      8.90000000E+01
      8.20000000E+01
      9.40000000E+01
      1.05000000E+02
      1.08000000E+02
      1.07000000E+02
      1.09000000E+02
      1.12000000E+02
      1.16000000E+02
      1.16000000E+02
      1.09000000E+02
      1.05000000E+02
      1.09000000E+02
      1.13000000E+02
      1.13000000E+02
    </axis>
    <axis name='RESID_1'>
      1.60525250E-03
      1.10677164E-03
      -1.85218337E-03
      -5.13633015E-03
      -7.20690424E-03
      3.87551088E-04
      9.91263334E-03
      -2.73375248E-04
      -4.50701732E-03
      1.21094997E-03
      -1.24082882E-02
      1.60395936E-03
      4.91866702E-03
      1.15160551E-03
      1.90310669E-03
      1.30047556E-03
      1.67095265E-03
      -2.80112494E-03
      -7.25180085E-04
      3.86423222E-03
      3.28836124E-03
      -1.54836988E-03
      -1.84596772E-03
      8.47157557E-03
      4.91826842E-03
      1.40089225E-02
      1.80548802E-02
      7.22399494E-03
      6.28187833E-03
      1.26498546E-02
      3.12507972E-02
      5.09641886E-01
      6.48733377E-02
      -1.30265981E-01
      4.42290120E-02
      3.34032252E-03
      9.51796025E-02
      -4.85188700E-02
      5.74680557E-03
      2.15852950E-02
      9.06899478E-03
      -1.21606495E-02
      -7.52428826E-03
      -3.38441879E-03
      -7.61007657E-03
      9.10909846E-02
      4.88096327E-02
      -1.04531702E-02
      5.35870381E-02
      -1.15518514E-02
      -3.68927903E-02
      -4.68388312E-02
    </axis>
    <axis name='RESID_2'>
      2.13167770E-03
      4.75632783E-04
      1.57564476E-01
      1.71655230E-02
      6.36147161E-05
      -9.40157846E-03
      -7.51482221E-05
      3.33210593E-03
      -3.14428359E-02
      2.34238221E-03
      -7.20726699E-03
      2.41971645E-03
      -2.41292873E-03
      -1.59388350E-03
      1.01478389E-02
      1.12548796E-02
      -8.29721149E-03
      -4.09343105E-04
      -8.86605761E-04
      1.48145491E-02
      -2.66985176E-03
      -2.75642029E-03
      -7.96684437E-03
      -7.10039516E-04
      3.89757752E-03
      -4.87752631E-03
      -5.47541305E-04
      -3.13312234E-03
      1.79462638E-02
      -1.56302899E-02
      -1.18021052E-02
      -4.26605530E-02
      -1.38322175E-01
      6.78980798E-02
      8.27792361E-02
      6.91229627E-02
      -2.24321447E-02
      2.22432204E-02
      -1.67645626E-02
      -8.29287153E-03
      8.55810568E-03
      4.80045471E-03
      -4.99752176E-04
      -7.74912024E-03
      -4.60919272E-03
      4.43371274E-02
      -3.80947217E-02
      -5.48671894E-02
      -7.53071308E-02
      2.68828366E-02
      4.20523100E-02
      4.09369403E-03
    </axis>
    <axis name='RESID_3'>
      5.40510565E-03
      6.26460509E-03
      1.00242399E-01
      -2.48334315E-02
      -3.84065032E-04
      1.13372579E-02
      -3.50134773E-03
      6.47163764E-03
      -4.86714672E-03
      -2.72864499E-03
      3.62418912E-04
      2.35687941E-03
      9.24106035E-03
      1.53210224E-03
      -1.24783935E-02
      -1.08373016E-02
      -2.03701109E-02
      3.69860255E-03
      -3.20553291E-03
      -1.35880080E-03
      1.90505181E-02
      -1.63662829E-03
      -1.20964330E-02
      -1.64687559E-02
      2.29504388E-02
      -1.18562765E-03
      -2.46092584E-02
      -1.08102812E-02
      -1.49952667E-02
      -4.11880016E-03
      -6.02431316E-03
      -7.50975311E-02
      5.23043692E-01
      6.67853504E-02
      8.52496736E-03
      -2.52418648E-02
      6.80639967E-02
      4.51626070E-03
      -1.90106872E-02
      -7.53675541E-03
      1.04148220E-02
      5.09477034E-03
      6.98635913E-03
      1.07595930E-02
      6.07361179E-03
      -6.81183115E-02
      -6.88898638E-02
      -1.18637092E-01
      -5.64152561E-02
      -1.00751556E-01
      -7.46941045E-02
      -3.81822721E-03
    </axis>
    <axis name='RESID_4'>
      2.07453538E-02
      1.46041932E-02
      1.19311124E-01
      -9.72166308E-04
      -1.02016376E-03
      -1.89485010E-02
      1.92784984E-02
      1.82635896E-02
      -3.18910554E-02
      1.39438352E-02
      7.64036272E-03
      4.51636297E-04
      -9.05497652E-03
      3.75710719E-04
      6.29782910E-04
      -2.12019635E-03
      -2.46235244E-02
      -5.03647607E-04
      -3.36121884E-03
      -6.65968237E-03
      1.91763323E-02
      2.04715319E-03
      1.55290598E-02
      6.91442110E-04
      1.77566912E-02
      -2.41135471E-02
      -5.82018634E-03
      1.10555289E-03
      1.11204796E-02
      6.80964906E-03
      -3.23397219E-02
      -1.73524618E-02
      2.20028073E-01
      -2.32409239E-01
      7.01776668E-02
      9.00027305E-02
      -5.44539876E-02
      -2.37015747E-02
      5.81810139E-02
      2.91194580E-02
      -1.31286476E-02
      1.44722452E-02
      -2.48242472E-03
      -2.07221461E-03
      2.60331784E-04
      5.39101958E-02
      4.00137603E-02
      -1.65553335E-02
      -7.13964477E-02
      -1.22110937E-02
      -1.58953480E-02
      -4.51234030E-03
    </axis>
    <axis name='ECC'>
      1.00614280E-01
      1.23671651E-01
      1.12877287E-01
      1.12877287E-01
      1.05313502E-01
      1.02219060E-01
      1.05997272E-01
      1.17559038E-01
      1.25991762E-01
      1.36275321E-01
      1.48697495E-01
      1.56181678E-01
      1.64034694E-01
      1.78717881E-01
      1.93966806E-01
      2.04047278E-01
      2.21826211E-01
      2.33968899E-01
      2.56549239E-01
      2.79779881E-01
      2.94567764E-01
      3.16815883E-01
      3.47587466E-01
      3.63320500E-01
      3.82526070E-01
      4.11685318E-01
      4.43518430E-01
      4.75211084E-01
      5.05758643E-01
      5.41436255E-01
      5.66215277E-01
      5.66215277E-01
      5.80223203E-01
      5.95631957E-01
      6.20518863E-01
      6.17436349E-01
      6.28115535E-01
      6.12066448E-01
      6.03058338E-01
      6.06446743E-01
      6.14685595E-01
      6.23808086E-01
      6.30419493E-01
      6.35233939E-01
      6.23602152E-01
      6.23602152E-01
      6.23602152E-01
      6.23602152E-01
      6.23602152E-01
      6.23602152E-01
      6.23602152E-01
      6.23602152E-01
    </axis>
    <axis name='POSANG'>
      6.80745087E+01
      7.06252289E+01
      6.99837112E+01
      6.67950287E+01
      6.10511208E+01
      6.02706680E+01
      5.47948151E+01
      5.44841881E+01
      5.38961487E+01
      5.56408806E+01
      5.60183792E+01
      5.43466606E+01
      5.13015976E+01
      5.20742798E+01
      5.26040840E+01
      5.23918228E+01
      5.20187950E+01
      5.20301895E+01
      5.20301895E+01
      5.17022743E+01
      5.04567604E+01
      4.94763794E+01
      4.85940781E+01
      4.76491127E+01
      4.65152168E+01
      4.57896118E+01
      4.46433372E+01
      4.37174454E+01
      4.30331306E+01
      4.19177132E+01
      4.16485634E+01
      4.16485634E+01
      4.31998940E+01
      4.49063606E+01
      4.52232552E+01
      4.60835876E+01
      4.66751595E+01
      4.78746605E+01
      4.78746605E+01
      4.83752823E+01
      4.87025414E+01
      4.90767174E+01
      4.84825478E+01
      4.74962349E+01
      4.71383896E+01
      4.71383896E+01
      4.71383896E+01
      4.71383896E+01
      4.71383896E+01
      4.71383896E+01
      4.71383896E+01
      4.71383896E+01
    </axis>
    <axis name='X0'>
      1.41059677E+02
      1.41055740E+02
      1.41063477E+02
      1.41066345E+02
      1.41072372E+02
      1.41074615E+02
      1.41071564E+02
      1.41075867E+02
      1.41073013E+02
      1.41076630E+02
      1.41075134E+02
      1.41086182E+02
      1.41094711E+02
      1.41103699E+02
      1.41111160E+02
      1.41138672E+02
      1.41149979E+02
      1.41185364E+02
      1.41206741E+02
      1.41226486E+02
      1.41261765E+02
      1.41257156E+02
      1.41184433E+02
      1.41268600E+02
      1.41383316E+02
      1.41566284E+02
      1.41732071E+02
      1.41773865E+02
      1.41885117E+02
      1.42064758E+02
      1.42117401E+02
      1.41713821E+02
      1.41901733E+02
      1.42108444E+02
      1.41591141E+02
      1.41545654E+02
      1.41617706E+02
      1.41677017E+02
      1.41165390E+02
      1.41239105E+02
      1.41467514E+02
      1.41041397E+02
      1.40758286E+02
      1.41174408E+02
      1.41169357E+02
      1.41149979E+02
      1.41149979E+02
      1.41149979E+02
      1.41149979E+02
      1.41149979E+02
      1.41149979E+02
      1.41149979E+02
    </axis>
    <axis name='Y0'>
      1.41366348E+02
      1.41365555E+02
      1.41374084E+02
      1.41381958E+02
      1.41394424E+02
      1.41403961E+02
      1.41410294E+02
      1.41423035E+02
      1.41424072E+02
      1.41423782E+02
      1.41428391E+02
      1.41430481E+02
      1.41417709E+02
      1.41402237E+02
      1.41396530E+02
      1.41378952E+02
      1.41354645E+02
      1.41338348E+02
      1.41319733E+02
      1.41318848E+02
      1.41302994E+02
      1.41271210E+02
      1.41221603E+02
      1.41244507E+02
      1.41298111E+02
      1.41405640E+02
      1.41477585E+02
      1.41472214E+02
      1.41525391E+02
      1.41688934E+02
      1.41630157E+02
      1.41271225E+02
      1.41278564E+02
      1.41286636E+02
      1.40786484E+02
      1.40828323E+02
      1.41305573E+02
      1.41843552E+02
      1.41497360E+02
      1.41381485E+02
      1.41400772E+02
      1.41018265E+02
      1.40953903E+02
      1.41248108E+02
      1.41251907E+02
      1.41354645E+02
      1.41354645E+02
      1.41354645E+02
      1.41354645E+02
      1.41354645E+02
      1.41354645E+02
      1.41354645E+02
    </axis>
    <axis name='FOUR_2'>
      1.11580351E-02
      5.27576590E-03
      7.88698066E-03
      3.23949009E-03
      2.89822277E-03
      -5.09589037E-04
      5.71405049E-04
      1.41554663E-03
      -1.90100900E-03
      -2.23663566E-03
      -1.25226111E-03
      3.76869575E-04
      1.97316962E-03
      -2.50794878E-03
      -3.39180510E-03
      -3.43924854E-03
      -7.79945077E-03
      -9.02083144E-03
      -7.64474506E-03
      -8.13735649E-03
      -5.34439133E-03
      -2.96092476E-03
      4.90271766E-03
      1.46491686E-04
      -4.36124206E-03
      -6.92452816E-03
      1.33495327E-04
      1.34334536E-02
      2.17253435E-02
      3.33928727E-02
      3.96603793E-02
      1.72000248E-02
      2.83111949E-02
      6.50929846E-03
      5.28053381E-03
      1.56284720E-02
      1.82867777E-02
      1.47940973E-02
      1.93001498E-02
      2.93228310E-02
      1.88517477E-02
      -4.67414269E-03
      -8.97605531E-03
      -9.70583223E-03
      -2.56776568E-02
      -1.57727376E-02
      -2.50760484E-02
      -2.23096907E-02
      -7.18046213E-03
      9.48737562E-03
      7.71264791E-01
      2.00654805E-01
    </axis>
    <axis name='THIRD_2'>
      9.34297498E-03
      6.67029002E-04
      -3.43044801E-03
      -4.69622342E-03
      -7.46710179E-03
      -7.37460610E-03
      -8.55458528E-03
      -9.37552005E-03
      -7.21777324E-03
      -4.47543710E-03
      -1.80006563E-03
      -7.73308740E-04
      2.57348642E-03
      4.46606148E-03
      4.00365377E-03
      6.29812386E-03
      7.05340737E-03
      6.44811708E-03
      9.67934355E-03
      8.85141734E-03
      1.09814908E-02
      1.09262159E-02
      1.21542430E-02
      1.89510155E-02
      2.73084790E-02
      3.57354023E-02
      4.00139652E-02
      3.34873311E-02
      2.16290224E-02
      2.02581510E-02
      1.83469187E-02
      2.39062607E-02
      -2.31812727E-02
      -5.02185198E-03
      -3.52141890E-03
      -6.69564120E-04
      -1.54381553E-02
      -8.32501613E-03
      3.24264122E-03
      5.44746732E-03
      3.40829743E-03
      5.21777850E-03
      9.44554154E-03
      -5.61647769E-03
      -2.15116516E-02
      -3.12349349E-02
      -2.97670327E-02
      7.55272508E-02
      2.73975078E-02
      -1.24840759E-01
      -3.43317240E-01
      -1.87917519E-02
    </axis>
  </array>
  <nsky>
    310
  </nsky>
</archangel>
